tfdlpack_gpu-0.1.3.data/purelib/tfdlpack/__init__.py
tfdlpack_gpu-0.1.3.data/purelib/tfdlpack/capsule_api.py
tfdlpack_gpu-0.1.3.data/purelib/tfdlpack/core.py
tfdlpack_gpu-0.1.3.data/purelib/tfdlpack/libinfo.py
tfdlpack_gpu-0.1.3.data/purelib/tfdlpack/libtfdlpack-tf-2.1.0.so
tfdlpack_gpu-0.1.3.data/purelib/tfdlpack/libtfdlpack-tf-2.2.0.so
tfdlpack_gpu-0.1.3.dist-info/METADATA
tfdlpack_gpu-0.1.3.dist-info/RECORD
tfdlpack_gpu-0.1.3.dist-info/WHEEL
tfdlpack_gpu-0.1.3.dist-info/top_level.txt
